MANIFEST.in
README.md
emoji_search.py
setup.py
slack_emoji_search.egg-info/PKG-INFO
slack_emoji_search.egg-info/SOURCES.txt
slack_emoji_search.egg-info/dependency_links.txt
slack_emoji_search.egg-info/entry_points.txt
slack_emoji_search.egg-info/requires.txt
slack_emoji_search.egg-info/top_level.txt