Metadata-Version: 1.0
Name: slack-emoji-search
Version: 0.0.1
Summary: Search across Slack for messages with a specific emoji.
Home-page: https://github.com/18F/emoji_search
Author: Micah Saul
Author-email: micah.sual@gsa.gov
License: CC0 1.0 Universal
Platform: UNKNOWN
